Metadata-Version: 1.0
Name: bq-upload
Version: 0.23
Summary: A python command line package, which makes it easy to upload files to BigQuery.
Home-page: https://www.domwoodman.com
Author: Dominic Woodman
Author-email: domwoodman@gmail.com
License: UNKNOWN
Platform: UNKNOWN
